daddario/__init__.py
daddario-0.0.1.dist-info/LICENSE
daddario-0.0.1.dist-info/METADATA
daddario-0.0.1.dist-info/WHEEL
daddario-0.0.1.dist-info/top_level.txt
daddario-0.0.1.dist-info/RECORD
